{
  "configurations": [
    {
      "name": "x64-Debug",
      "generator": "Ninja",
      "configurationType": "Debug",
      "inheritEnvironments": [ "msvc_x64_x64" ],
      "buildRoot": "${projectDir}\\out\\build\\${name}",
      "installRoot": "${projectDir}\\out\\install\\${name}",
      "cmakeCommandArgs": "",
      "buildCommandArgs": "",
      "ctestCommandArgs": "",
      "variables": [
        {
          "name": "CMAKE_TOOLCHAIN_FILE",
          "value": "C:\\Users\\Kate\\vcpkg\\scripts\\buildsystems\\vcpkg.cmake"
        },
        {
          "name": "VCPKG_TARGET_TRIPLET",
          "value": "x64-windows"
        },
        {
          "name": "CMAKE_CXX_COMPILER",
          "value": "C:\\Program Files\\LLVM\\bin\\clang++.exe",
          "type": "FILEPATH"
        },
        {
          "name": "CMAKE_C_COMPILER",
          "value": "C:\\Program Files\\LLVM\\bin\\clang.exe",
          "type": "FILEPATH"
        }
      ]
    }
  ]
}